{
	"common": {
		"name": "snapcast",
		"version": "0.0.1",
		"news": {
			"0.0.1": {
				"en": "initial release",
				"de": "Erstveröffentlichung",
				"ru": "Начальная версия",
				"pt": "lançamento inicial",
				"nl": "Eerste uitgave",
				"fr": "Première version",
				"it": "Versione iniziale",
				"es": "Versión inicial",
				"pl": "Pierwsze wydanie",
				"zh-cn": "首次出版"
			}
		},
		"title": "Snapcast",
		"titleLang": {
			"en": "Snapcast",
			"de": "Snapcast",
			"ru": "Snapcast",
			"pt": "Snapcast",
			"nl": "Snapcast",
			"fr": "Snapcast",
			"it": "Snapcast",
			"es": "Snapcast",
			"pl": "Snapcast",
			"zh-cn": "快照"
		},
		"desc": {
			"en": "multiroom client-server audio player",
			"de": "Multiroom-Client-Server-Audioplayer",
			"ru": "многокомнатный клиент-серверный аудиоплеер",
			"pt": "reprodutor de áudio cliente-servidor multiroom",
			"nl": "multiroom client-server audiospeler",
			"fr": "lecteur audio client-serveur multiroom",
			"it": "lettore audio client-server multiroom",
			"es": "reproductor de audio cliente-servidor multisala",
			"pl": "Multiroom odtwarzacz audio klient-serwer",
			"zh-cn": "多房间客户端服务器音频播放器"
		},
		"authors": [
			"Jampr <jampr@online.de>"
		],
		"keywords": [
			"multiroom",
			"client-server audio player"
		],
		"license": "MIT",
		"platform": "Javascript/Node.js",
		"main": "build/main.js",
		"icon": "snapcast.png",
		"enabled": true,
		"extIcon": "https://github.com/jampr21/ioBroker.snapcast/blob/main/admin/snapcast.png?raw=true",
		"readme": "https://raw.githubusercontent.com/jampr21/ioBroker.snapcast/main/README.md",
		"loglevel": "info",
		"mode": "daemon",
		"type": "multimedia",
		"compact": true,
		"connectionType": "local",
		"dataSource": "push",
		"materialize": true,
		"dependencies": [
			{
				"js-controller": ">=2.0.0"
			}
		]
	},
	"native": {
		"host": "192.168.1.3",
		"port": "1780",
		"media_path": "/opt/iobroker",
		"tcp_socket_host": "192.168.1.3",
		"tcp_socket_": "3333"
	},
	"objects": [],
	"instanceObjects": []
}
